qpdb/__init__.py
qpdb/intersphinx.py
qpdb/log_utils.py
qpdb/lookup.py
qpdb/py.typed
qpdb/web_parsing.py
qpdb-0.2.0.dist-info/LICENSE
qpdb-0.2.0.dist-info/METADATA
qpdb-0.2.0.dist-info/WHEEL
qpdb-0.2.0.dist-info/entry_points.txt
qpdb-0.2.0.dist-info/top_level.txt
qpdb-0.2.0.dist-info/RECORD
