Metadata-Version: 2.1
Name: qpdb
Version: 0.2.0
Summary: Pandas API reference
Home-page: https://github.com/qu-arx/qp
Author: Louis Maddox
Author-email: louismmx@gmail.com
Maintainer: Louis Maddox
Maintainer-email: louismmx@gmail.com
License: MIT
Project-URL: Bug Tracker, https://github.com/qu-arx/qp/issues
Project-URL: Source Code, https://github.com/qu-arx/qp
Platform: UNKNOWN
Classifier: Development Status :: 4 - Beta
Classifier: Intended Audience :: Developers
Classifier: Natural Language :: English
Classifier: License :: OSI Approved :: MIT License
Classifier: Operating System :: OS Independent
Classifier: Programming Language :: Python
Classifier: Programming Language :: Python :: Implementation :: CPython
Classifier: Programming Language :: Python :: 3
Classifier: Programming Language :: Python :: 3.10
Classifier: Intended Audience :: Developers
Classifier: Topic :: Education
Requires-Python: >=3.10
License-File: LICENSE
Requires-Dist: bs4
Requires-Dist: defopt
Requires-Dist: html5lib
Requires-Dist: httpx
Requires-Dist: sphinx
Requires-Dist: sphobjinv
Provides-Extra: dev
Requires-Dist: coverage[toml] (>=5.5) ; extra == 'dev'
Requires-Dist: pytest ; extra == 'dev'
Requires-Dist: pre-commit ; extra == 'dev'
Provides-Extra: tests
Requires-Dist: coverage[toml] (>=5.5) ; extra == 'tests'
Requires-Dist: pytest ; extra == 'tests'
